codechecker_api_shared/__init__.py
codechecker_api_shared/constants.py
codechecker_api_shared/ttypes.py
codechecker_api_shared-6.39.0.dist-info/LICENSE
codechecker_api_shared-6.39.0.dist-info/METADATA
codechecker_api_shared-6.39.0.dist-info/WHEEL
codechecker_api_shared-6.39.0.dist-info/top_level.txt
codechecker_api_shared-6.39.0.dist-info/RECORD
