Metadata-Version: 2.1
Name: codechecker-api-shared
Version: 6.39.0
Summary: Shared API stub types package for the CodeChecker API.
Home-page: https://github.com/Ericsson/codechecker
License: UNKNOWN
Project-URL: Bug Reports, https://github.com/Ericsson/codechecker/issues
Project-URL: Source, https://github.com/Ericsson/codechecker/tree/master/web/api
Keywords: codechecker thrift api library
Platform: UNKNOWN
Classifier: Development Status :: 3 - Alpha
Classifier: Intended Audience :: Developers
Classifier: Programming Language :: Python :: 2
Classifier: Programming Language :: Python :: 3
Requires-Python: >=2.7,
